blog_image_auto_syncer/__init__.py
blog_image_auto_syncer/vanjor.py
blog_image_auto_syncer/commands/__init__.py
blog_image_auto_syncer/commands/test.py
blog_image_auto_syncer-0.0.3.dist-info/LICENSE
blog_image_auto_syncer-0.0.3.dist-info/METADATA
blog_image_auto_syncer-0.0.3.dist-info/WHEEL
blog_image_auto_syncer-0.0.3.dist-info/entry_points.txt
blog_image_auto_syncer-0.0.3.dist-info/top_level.txt
blog_image_auto_syncer-0.0.3.dist-info/RECORD
