Metadata-Version: 2.1
Name: blog-image-auto-syncer
Version: 0.0.3
Summary: auto download image from your blog and sync to github
Home-page: https://github.com/vanjor/blog_image_auto_syncer
Author: vanjor
Author-email: vanjor2008@gmail.com
License: UNKNOWN
Platform: UNKNOWN
Classifier: Programming Language :: Python :: 3
Classifier: License :: OSI Approved :: MIT License
Classifier: Operating System :: OS Independent
